pro_football_reference_web_scraper_v2/__init__.py
pro_football_reference_web_scraper_v2/_version.py
pro_football_reference_web_scraper_v2/player_game_log.py
pro_football_reference_web_scraper_v2/player_splits.py
pro_football_reference_web_scraper_v2/team_game_log.py
pro_football_reference_web_scraper_v2/team_splits.py
pro_football_reference_web_scrape_v2-0.2.0.dist-info/LICENSE
pro_football_reference_web_scrape_v2-0.2.0.dist-info/METADATA
pro_football_reference_web_scrape_v2-0.2.0.dist-info/WHEEL
pro_football_reference_web_scrape_v2-0.2.0.dist-info/top_level.txt
pro_football_reference_web_scrape_v2-0.2.0.dist-info/RECORD
