Metadata-Version: 2.1
Name: pro-football-reference-web-scrape-v2
Version: 0.2.0
Summary: Stats web scraper of Pro Football Reference
Author-email: Matthew Kim <mjk2244@columbia.edu>
License: Apache License
Project-URL: repository, https://github.com/mjk2244/pro-football-reference-web-scraper
Classifier: Development Status :: 2 - Pre-Alpha
Classifier: Programming Language :: Python :: Implementation :: CPython
Classifier: Programming Language :: Python :: Implementation :: PyPy
Classifier: Programming Language :: Python :: 3
Classifier: Programming Language :: Python :: 3.7
Classifier: Programming Language :: Python :: 3.8
Classifier: Programming Language :: Python :: 3.9
Classifier: Programming Language :: Python :: 3.10
Classifier: Programming Language :: Python :: 3.11
Requires-Python: >=3.8
License-File: LICENSE
Requires-Dist: beautifulsoup4 >=4.9.0
Requires-Dist: requests >=2.28.2
Requires-Dist: pandas >=1.5.3
Requires-Dist: haversine >=2.4.0
Provides-Extra: develop
Requires-Dist: black >=22 ; extra == 'develop'
Requires-Dist: bump2version >=1.0.0 ; extra == 'develop'
Requires-Dist: check-manifest ; extra == 'develop'
Requires-Dist: flake8 >=3.7.8 ; extra == 'develop'
Requires-Dist: flake8-black >=0.2.1 ; extra == 'develop'
Requires-Dist: flake8-pyproject ; extra == 'develop'
Requires-Dist: mypy ; extra == 'develop'
Requires-Dist: pytest >=4.3.0 ; extra == 'develop'
Requires-Dist: pytest-cov >=4.0.0 ; extra == 'develop'
Requires-Dist: twine ; extra == 'develop'
Requires-Dist: wheel ; extra == 'develop'
